{
  "metadata": {
    "ticker": "BTC-USD",
    "period": 897,
    "ma_type": "SMA",
    "generated_at": "2025-09-21T09:44:01.406581",
    "data_points": 3126,
    "date_range": {
      "start": "2017-03-01T00:00:00.000000000",
      "end": "2025-09-20T00:00:00.000000000"
    }
  },
  "analytics": {
    "summary": {
      "ticker": "BTC-USD",
      "period": 897,
      "ma_type": "SMA",
      "data_points": 3126,
      "start_date": "2017-03-01 00:00:00",
      "end_date": "2025-09-20 00:00:00",
      "date_range_days": 3125
    },
    "risk_metrics": {
      "sharpe_ratio": 13.484932713046808,
      "sortino_ratio": 59.51971510970287,
      "max_drawdown": 8.889860973035198,
      "volatility": 2.8375198567268582,
      "var_95": -0.028355067767164156,
      "cvar_95": -0.08166135079448285
    },
    "performance_metrics": {
      "total_return": 14506.874649177738,
      "annualized_return": 49.468577335351085,
      "cagr": 49.468577335351085,
      "calmar_ratio": 5.564606407839177,
      "information_ratio": 14.189773595572666
    },
    "trend_metrics": {
      "trend_direction": "Upward",
      "trend_strength": "Very Strong",
      "r_squared": 0.9084230937344637,
      "smoothness_factor": 0.9985959197081605,
      "linear_slope": 17.532545318882736
    },
    "statistical_metrics": {
      "mean_return": 0.0015977684261863454,
      "std_deviation": 0.0017874694955016415,
      "skewness": 2.0393498376504198,
      "kurtosis": 6.667059482758912,
      "autocorrelation": 0.9966355140526403,
      "price_mean": 20257.328180056244,
      "price_median": 16055.349855420847
    }
  }
}
