{
  "ticker": "HAL",
  "timestamp": "2025-07-14T11:19:42.200676",
  "overall_score": 5.017588306402649,
  "signal": "HOLD",
  "confidence": 0.6250879415320132,
  "factors": [
    {
      "name": "risk",
      "contribution": -3.413296275639505,
      "weight": 0.25,
      "score": -13.65318510255802,
      "performance_metrics": {
        "avg_score": 0.0,
        "score_volatility": 1.0,
        "avg_contribution": 0.0,
        "contribution_consistency": 0.5,
        "score_trend": 0.0,
        "contribution_trend": 0.0,
        "factor_efficiency": 0.5,
        "signal_accuracy": 0.5
      }
    },
    {
      "name": "momentum",
      "contribution": 5.683028543036309,
      "weight": 0.2,
      "score": 28.415142715181545,
      "performance_metrics": {
        "avg_score": 0.0,
        "score_volatility": 1.0,
        "avg_contribution": 0.0,
        "contribution_consistency": 0.5,
        "score_trend": 0.0,
        "contribution_trend": 0.0,
        "factor_efficiency": 0.5,
        "signal_accuracy": 0.5
      }
    },
    {
      "name": "trend",
      "contribution": 1.2479548721973037,
      "weight": 0.25,
      "score": 4.991819488789215,
      "performance_metrics": {
        "avg_score": 0.0,
        "score_volatility": 1.0,
        "avg_contribution": 0.0,
        "contribution_consistency": 0.5,
        "score_trend": 0.0,
        "contribution_trend": 0.0,
        "factor_efficiency": 0.5,
        "signal_accuracy": 0.5
      }
    },
    {
      "name": "risk_adjusted",
      "contribution": -0.06597986982218781,
      "weight": 0.18,
      "score": -0.36655483234548786,
      "performance_metrics": {
        "avg_score": 0.0,
        "score_volatility": 1.0,
        "avg_contribution": 0.0,
        "contribution_consistency": 0.5,
        "score_trend": 0.0,
        "contribution_trend": 0.0,
        "factor_efficiency": 0.5,
        "signal_accuracy": 0.5
      }
    },
    {
      "name": "mean_reversion",
      "contribution": 0.13309224818426682,
      "weight": 0.05,
      "score": 2.6618449636853363,
      "performance_metrics": {
        "avg_score": 0.0,
        "score_volatility": 1.0,
        "avg_contribution": 0.0,
        "contribution_consistency": 0.5,
        "score_trend": 0.0,
        "contribution_trend": 0.0,
        "factor_efficiency": 0.5,
        "signal_accuracy": 0.5
      }
    },
    {
      "name": "volume_liquidity",
      "contribution": 1.4327887884464618,
      "weight": 0.07,
      "score": 20.46841126352088,
      "performance_metrics": {
        "avg_score": 0.0,
        "score_volatility": 1.0,
        "avg_contribution": 0.0,
        "contribution_consistency": 0.5,
        "score_trend": 0.0,
        "contribution_trend": 0.0,
        "factor_efficiency": 0.5,
        "signal_accuracy": 0.5
      }
    }
  ],
  "regime_info": {
    "volatility_regime": "normal",
    "current_vix": 16.399999618530273,
    "threshold_adjustments": {
      "strong_buy": 0,
      "buy": 0,
      "sell": 0,
      "strong_sell": 0
    },
    "weight_adjustments": {
      "risk": 1.0,
      "momentum": 1.0,
      "trend": 1.0,
      "risk_adj": 1.0,
      "mean_rev": 1.0,
      "volume": 1.0
    }
  },
  "performance_summary": {
    "total_contribution": 11.976140597326035,
    "positive_contribution": 8.496864451864342,
    "negative_contribution": -3.4792761454616925,
    "contribution_balance": 0.7094234540221825,
    "factor_diversification": 0.8341355532588375,
    "weight_efficiency": 0.4469982340476596,
    "factor_count": 6,
    "dominant_factor": "momentum"
  }
}
