{
  "ticker": "UHS",
  "timestamp": "2025-07-14T09:24:44.646483",
  "overall_score": -6.155991179520618,
  "signal": "HOLD",
  "confidence": 0.630779955897603,
  "factors": [
    {
      "name": "risk",
      "contribution": -2.7280056618898096,
      "weight": 0.28,
      "score": -9.742877363892177,
      "performance_metrics": {
        "avg_score": 0.0,
        "score_volatility": 1.0,
        "avg_contribution": 0.0,
        "contribution_consistency": 0.5,
        "score_trend": 0.0,
        "contribution_trend": 0.0,
        "factor_efficiency": 0.5,
        "signal_accuracy": 0.5
      }
    },
    {
      "name": "momentum",
      "contribution": -2.60974039624007,
      "weight": 0.18,
      "score": -14.498557756889278,
      "performance_metrics": {
        "avg_score": 0.0,
        "score_volatility": 1.0,
        "avg_contribution": 0.0,
        "contribution_consistency": 0.5,
        "score_trend": 0.0,
        "contribution_trend": 0.0,
        "factor_efficiency": 0.5,
        "signal_accuracy": 0.5
      }
    },
    {
      "name": "trend",
      "contribution": 0.17293735831268522,
      "weight": 0.23,
      "score": 0.75190155788124,
      "performance_metrics": {
        "avg_score": 0.0,
        "score_volatility": 1.0,
        "avg_contribution": 0.0,
        "contribution_consistency": 0.5,
        "score_trend": 0.0,
        "contribution_trend": 0.0,
        "factor_efficiency": 0.5,
        "signal_accuracy": 0.5
      }
    },
    {
      "name": "risk_adjusted",
      "contribution": -1.3463085671515411,
      "weight": 0.18,
      "score": -7.4794920397307845,
      "performance_metrics": {
        "avg_score": 0.0,
        "score_volatility": 1.0,
        "avg_contribution": 0.0,
        "contribution_consistency": 0.5,
        "score_trend": 0.0,
        "contribution_trend": 0.0,
        "factor_efficiency": 0.5,
        "signal_accuracy": 0.5
      }
    },
    {
      "name": "mean_reversion",
      "contribution": 0.09376466846694256,
      "weight": 0.05,
      "score": 1.8752933693388512,
      "performance_metrics": {
        "avg_score": 0.0,
        "score_volatility": 1.0,
        "avg_contribution": 0.0,
        "contribution_consistency": 0.5,
        "score_trend": 0.0,
        "contribution_trend": 0.0,
        "factor_efficiency": 0.5,
        "signal_accuracy": 0.5
      }
    },
    {
      "name": "volume_liquidity",
      "contribution": 0.261361418981175,
      "weight": 0.08,
      "score": 3.2670177372646876,
      "performance_metrics": {
        "avg_score": 0.0,
        "score_volatility": 1.0,
        "avg_contribution": 0.0,
        "contribution_consistency": 0.5,
        "score_trend": 0.0,
        "contribution_trend": 0.0,
        "factor_efficiency": 0.5,
        "signal_accuracy": 0.5
      }
    }
  ],
  "regime_info": {
    "volatility_regime": "normal",
    "current_vix": 16.399999618530273,
    "threshold_adjustments": {
      "strong_buy": 0,
      "buy": 0,
      "sell": 0,
      "strong_sell": 0
    },
    "weight_adjustments": {
      "risk": 1.0,
      "momentum": 1.0,
      "trend": 1.0,
      "risk_adj": 1.0,
      "mean_rev": 1.0
    }
  },
  "performance_summary": {
    "total_contribution": 7.212118071042224,
    "positive_contribution": 0.5280634457608028,
    "negative_contribution": -6.684054625281421,
    "contribution_balance": 0.07320876222458712,
    "factor_diversification": 0.8449452659957428,
    "weight_efficiency": 0.6326316442217489,
    "factor_count": 6,
    "dominant_factor": "risk"
  }
}
